prodigy/__init__.py
prodigy/cache.sqlite
prodigy/gameData.py
prodigy/gameStatus.py
prodigy/get_asset.py
prodigy/get_friend_requests.py
prodigy/get_userID.py
prodigy/player.py
prodigy/prodigy.py
prodigy/tokenify.py
prodigy_api-3.0.0.dist-info/LICENSE
prodigy_api-3.0.0.dist-info/WHEEL
prodigy_api-3.0.0.dist-info/METADATA
prodigy_api-3.0.0.dist-info/RECORD
