Metadata-Version: 2.1
Name: prodigy-api
Version: 3.0.0
Summary: Python Package to Hack Prodigy The Math Game
Home-page: https://github.com/ProdigyAPI/ProdigyAPIWrapperInPython
License: MIT
Author: ProdigyAPI
Author-email: hostedpostedsite@gmail.com
Requires-Python: >=3.8,<4.0
Classifier: License :: OSI Approved :: MIT License
Classifier: Programming Language :: Python :: 3
Classifier: Programming Language :: Python :: 3.8
Classifier: Programming Language :: Python :: 3.9
Requires-Dist: beautifulsoup4 (>=4.9.3,<5.0.0)
Requires-Dist: lxml (>=4.6.3,<5.0.0)
Requires-Dist: requests (>=2.25.1,<3.0.0)
Requires-Dist: requests-cache (>=0.6.4,<0.7.0)
Project-URL: Documentation, https://prodigy.readthedocs.io/en/latest/
Project-URL: Repository, https://github.com/ProdigyAPI/ProdigyAPIWrapperInPython
